akismet/__init__.py
akismet/exceptions.py
akismet/tests.py
python_akismet-0.4.3.dist-info/LICENSE
python_akismet-0.4.3.dist-info/METADATA
python_akismet-0.4.3.dist-info/WHEEL
python_akismet-0.4.3.dist-info/pbr.json
python_akismet-0.4.3.dist-info/top_level.txt
python_akismet-0.4.3.dist-info/RECORD
