Metadata-Version: 2.1
Name: python-akismet
Version: 0.4.3
Summary: Akismet v1.1 module for Python.
Home-page: https://github.com/Nekmo/python-akismet
Author: Nekmo
Author-email: contacto@nekmo.com
License: MIT
Download-URL: https://github.com/Nekmo/python-akismet/archive/master.zip
Keywords: akismet,spam,protection,comments
Platform: universal
Classifier: License :: OSI Approved :: MIT License
Classifier: Programming Language :: Python :: 2.6
Classifier: Programming Language :: Python :: 2.7
Classifier: Programming Language :: Python :: 2 :: Only
Classifier: Natural Language :: English
Classifier: Development Status :: 1 - Planning
Provides: akismet
License-File: LICENSE
Requires-Dist: requests
